Workbook

Sheet Price Calculator
F3: Ultieme Prijscalculator - Pro V2.0
B7: SKU-code # | D7: C0001 | F7: Productnaam | I7: Houder | O7: Datum gewijzigd | Q7: 45658
B10: Onderdelen per serie | D10: =IF($F$12="Farmloop",$C$79,1) -> 1
E11: Formaat: | F11: Klein
D12: TEST12 | E12: Print modus: | F12: single
B13: Printkosten
B14: Onderdeel # | C14: Aantal | D14: Filament | H14: Filament (g) | I14: Printer | L14: UUR | M14: MIN | N14: Filamentkosten | P14: Printerafschrijving | R14: Elektriciteitskosten
B15: Lade | C15: 1 | D15: Bambu Lab PETG HF | H15: 80 | I15: Bambu Lab P2S Combo | L15: 2 | M15: 30 | N15: =IFERROR(ROUND(C15*H15/1000*VLOOKUP(D15,Materials!C:G,5,FALSE)/IF($F$12="Farmloop",$C$79,1),2),"-") -> 1.2 | O15: =Input!$C$13 -> € | P15: =IFERROR(ROUND((L15+(M15/60))*C15*VLOOKUP(I15,Printers!B:H,7,FALSE)/IF($F$12="Farmloop",$C$79,1),2),"-") -> 0.56 | Q15: =Input!$C$13 -> € | R15: =IFERROR(ROUND((L15+(M15/60))*C15*VLOOKUP(I15,Printers!B:J,9,FALSE)/1000*Input!$C$10/IF($F$12="Farmloop",$C$79,1),2),"-") -> 0.13 | S15: =Input!$C$13 -> €
N16: =IFERROR(ROUND(C16*H15/1000*VLOOKUP(D16,Materials!C:G,5,FALSE),2),"-") -> - | O16: =Input!$C$13 -> € | P16: =IFERROR(ROUND((L16+(M16/60))*C16*VLOOKUP(I16,Printers!B:H,7,FALSE),2),"-") -> - | Q16: =Input!$C$13 -> € | R16: =IFERROR(ROUND((L16+(M16/60))*C16*VLOOKUP(I16,Printers!B:J,9,FALSE)/1000*Input!$C$10,2),"-") -> - | S16: =Input!$C$13 -> €
N17: =IFERROR(ROUND(C17*H17/1000*VLOOKUP(D17,Materials!C:G,5,FALSE),2),"-") -> - | O17: =Input!$C$13 -> € | P17: =IFERROR(ROUND((L17+(M17/60))*C17*VLOOKUP(I17,Printers!B:H,7,FALSE),2),"-") -> - | Q17: =Input!$C$13 -> € | R17: =IFERROR(ROUND((L17+(M17/60))*C17*VLOOKUP(I17,Printers!B:J,9,FALSE)/1000*Input!$C$10,2),"-") -> - | S17: =Input!$C$13 -> €
N18: =IFERROR(ROUND(C18*H18/1000*VLOOKUP(D18,Materials!C:G,5,FALSE),2),"-") -> - | O18: =Input!$C$13 -> € | P18: =IFERROR(ROUND((L18+(M18/60))*C18*VLOOKUP(I18,Printers!B:H,7,FALSE),2),"-") -> - | Q18: =Input!$C$13 -> € | R18: =IFERROR(ROUND((L18+(M18/60))*C18*VLOOKUP(I18,Printers!B:J,9,FALSE)/1000*Input!$C$10,2),"-") -> - | S18: =Input!$C$13 -> € | V18: ¬
N19: =IFERROR(ROUND(C19*H19/1000*VLOOKUP(D19,Materials!C:G,5,FALSE),2),"-") -> - | O19: =Input!$C$13 -> € | P19: =IFERROR(ROUND((L19+(M19/60))*C19*VLOOKUP(I19,Printers!B:H,7,FALSE),2),"-") -> - | Q19: =Input!$C$13 -> € | R19: =IFERROR(ROUND((L19+(M19/60))*C19*VLOOKUP(I19,Printers!B:J,9,FALSE)/1000*Input!$C$10,2),"-") -> - | S19: =Input!$C$13 -> €
N20: =IFERROR(ROUND(C20*H20/1000*VLOOKUP(D20,Materials!C:G,5,FALSE),2),"-") -> - | O20: =Input!$C$13 -> € | P20: =IFERROR(ROUND((L20+(M20/60))*C20*VLOOKUP(I20,Printers!B:H,7,FALSE),2),"-") -> - | Q20: =Input!$C$13 -> € | R20: =IFERROR(ROUND((L20+(M20/60))*C20*VLOOKUP(I20,Printers!B:J,9,FALSE)/1000*Input!$C$10,2),"-") -> - | S20: =Input!$C$13 -> €
B21: Totaal | N21: =SUM(N15:N20) -> 1.2 | O21: =Input!$C$13 -> € | P21: =SUM(P15:P20) -> 0.56 | Q21: =Input!$C$13 -> € | R21: =SUM(R15:R20) -> 0.13 | S21: =Input!$C$13 -> €
B24: Verbruiksartikelen en Verpakking | I24: Kosten | N24: Offerte | U24: Marge % | V24: 50
B25: Omschrijving | D25: Aantal | E25: ="Kosten per stuk"&" $" -> Kosten per stuk $ | F25: Totale kosten | I25: Kosten | K25: Waarde | N25: Offerte | R25: Waarde
B26: Doos | D26: =IF($D$7="Klein",1,1) -> 1 | E26: =IF($F$11="Klein",0.5,0.45) -> 0.5 | F26: =IF((D26*E26)=0,"-",D26*E26) -> 0.5 | G26: =Input!$C$13 -> € | I26: Filament | K26: =$N$21 -> 1.2 | L26: =Input!$C$13 -> € | N26: Totale productiekosten | R26: =K35 -> 3.96 | S26: =Input!$C$13 -> € | U26: Verkoopprijs | V26: =Input!$C$13&R29 -> €5,94
B27: Vulmateriaal | D27: 1 | E27: =IF($F$11="Klein",0,0.1) -> 0 | F27: =IF((D27*E27)=0,"-",D27*E27) -> - | G27: =Input!$C$13 -> € | I27: Printerafschrijving | K27: =$P$21 -> 0.56 | L27: =Input!$C$13 -> € | N27: Marge | R27: =V24 -> 50 | S27: %
B28: Label | D28: 1 | E28: =IF($F$11="Klein",0,0.2) -> 0 | F28: =IF((D28*E28)=0,"-",D28*E28) -> - | G28: =Input!$C$13 -> € | I28: Elektriciteit | K28: =$R$21 -> 0.13 | L28: =Input!$C$13 -> € | N28: Margebedrag | R28: =ROUND(R26*R27/100,2) -> 1.98 | S28: =Input!$C$13 -> € | U28: Productiekosten | V28: =Input!$C$13&K35 -> €3,96
B29: Sticker | D29: 1 | E29: =IF($F$11="Klein",0,0.1) -> 0 | F29: =IF((D29*E29)=0,"-",D29*E29) -> - | G29: =Input!$C$13 -> € | I29: Verbruiksartikelen en Verpakking | K29: =$F$34 -> 0.5 | L29: =Input!$C$13 -> € | N29: Totale prijs | R29: =R26+R28 -> 5.94 | S29: =Input!$C$13 -> €
F30: =IF((D30*E30)=0,"-",D30*E30) -> - | G30: =Input!$C$13 -> € | I30: Voorbereiding | K30: =ROUND(E43*(Input!$C$11/60),2) -> 0.33 | L30: =Input!$C$13 -> € | N30: BTW (21%) | R30: =ROUND(R29*Input!$C$16,2) -> 1.25 | S30: =Input!$C$13 -> € | U30: Winst | V30: =Input!$C$13&K59 -> €1,98
F31: =IF((D31*E31)=0,"-",D31*E31) -> - | G31: =Input!$C$13 -> € | I31: Nabewerking | K31: =ROUND(E49*(Input!$C$11/60),2) -> 0.33 | L31: =Input!$C$13 -> € | N31: Verkoopprijs incl. BTW | R31: =R29+R30 -> 7.19 | S31: =Input!$C$13 -> €
F32: =IF((D32*E32)=0,"-",D32*E32) -> - | G32: =Input!$C$13 -> € | I32: Verzending en Afhandeling | K32: =E58 -> 0.33333333 | L32: =Input!$C$13 -> €
I33: Abonnementen | K33: =Input!C15/Input!C14 -> 0.5 | L33: =Input!$C$13 -> €
B34: Totaal | F34: =SUM(F26:F32) -> 0.5 | G34: =Input!$C$13 -> € | I34: Subtotalen | K34: =SUM(K26:K33) -> 3.8833333 | L34: =Input!$C$13 -> €
I35: Inclusief mislukkingen | K35: =ROUND(K34*(Input!C12/100)+K34,2) -> 3.96 | L35: =Input!$C$13 -> €
B37: Arbeid | U37: Arbeidstijd | V37: =SUM(E43,E49) &" mins" -> 2 mins
B38: Voorbereiding | D38: Totale tijd | E38: Tijd
B40: Modelvoorbereiding | D40: =IF($F$11="Klein",0.5,1) -> 0.5 | E40: =D40/$D$10 -> 0.5 | F40: min
B41: Slicen | D41: =IF($F$11="Klein",0.5,1) -> 0.5 | E41: =D41/$D$10 -> 0.5 | F41: min
B42: Overdracht & Start | D42: =IF($F$11="Klein",0,1) -> 0 | E42: =D42/$D$10 -> 0 | F42: min
B43: Som | E43: =SUM(E40:E42) -> 1 | F43: min
B45: Nabewerking | D45: Totale tijd | E45: Tijd
B46: Verwijderen van print | D46: =IF($D$11="Klein",0.5,0.5) -> 0.5 | E46: =D46/$D$10 -> 0.5 | F46: min
B47: Supports verwijderen | D47: =IF($D$11="Klein",0,0) -> 0 | E47: =D47/$D$10 -> 0 | F47: min | U47: Aanbevolen prijs (incl. BTW)
B48: Aanvullend werk | D48: =IF($F$11="Klein",0.5,1) -> 0.5 | E48: =D48/$D$10 -> 0.5 | F48: min | U48: Doel winst | V48: 3
B49: Som | E49: =SUM(E46:E48) -> 1 | F49: min
U50: Shopify Basic | V50: =ROUND((K35+V48+VLOOKUP("Shopify Basic",Fees!B:J,9,FALSE))/(1-Input!$C$16/(1+Input!$C$16)-VLOOKUP("Shopify Basic",Fees!B:J,8,FALSE)),2) -> 9.36
U51: Etsy | V51: =ROUND((K35+V48+VLOOKUP("Etsy ",Fees!B:J,9,FALSE))/(1-Input!$C$16/(1+Input!$C$16)-VLOOKUP("Etsy ",Fees!B:J,8,FALSE)),2) -> 10.13
U52: Bol – Brievenbus | V52: =ROUND((K35+V48+VLOOKUP("Bol.com",Fees!B:J,9,FALSE)+VLOOKUP("Bol.com",Fees!B:J,8,FALSE)*4.1)/(1-Input!$C$16/(1+Input!$C$16)-VLOOKUP("Bol.com",Fees!B:J,8,FALSE)),2) -> 12.97
B53: Verzending | I53: Winst-/Kostenberekening
B54: Verzending | E54: Kosten | K54: 0 | L54: 0.05 | M54: 0.1 | N54: 0.2 | O54: 0.3 | Q54: 0.5 | U54: Bol – Pakket | V54: =ROUND((K35+V48+VLOOKUP("Bol.com",Fees!B:J,9,FALSE)+VLOOKUP("Bol.com",Fees!B:J,8,FALSE)*6.5)/(1-Input!$C$16/(1+Input!$C$16)-VLOOKUP("Bol.com",Fees!B:J,8,FALSE)),2) -> 13.5
I55: Zonder kosten
B56: Verzendkosten (bij gratis verzending) | E56: 0 | F56: =Input!$C$13 -> € | I56: ="Prijzen met korting" -> Prijzen met korting | K56: =R29 -> 5.94 | L56: =K56-(K56*L54) -> 5.643 | M56: =K56-(K56*M54) -> 5.346 | N56: =K56-(K56*N54) -> 4.752 | O56: =K56-(K56*O54) -> 4.158 | Q56: =K56-(K56*Q54) -> 2.97
B57: Verwerkingstijd | E57: 1 | F57: min | I57: ="Productiekosten" -> Productiekosten | K57: =$K$35 -> 3.96 | L57: =$K$35 -> 3.96 | M57: =$K$35 -> 3.96 | N57: =$K$35 -> 3.96 | O57: =$K$35 -> 3.96 | Q57: =$K$35 -> 3.96
B58: Som | E58: =E56+E57/60*Input!C11 -> 0.33333333 | F58: =Input!$C$13 -> € | I58: Kortingsbedrag | K58: 0 | L58: =K56-L56 -> 0.297 | M58: =K56-M56 -> 0.594 | N58: =K56-N56 -> 1.188 | O58: =K56-O56 -> 1.782 | Q58: =K56-Q56 -> 2.97
I59: ="Potentiële winst" &" ("&Input!C13&")" -> Potentiële winst (€) | K59: =K56-K58-R26 -> 1.98 | L59: =K56-L58-R26 -> 1.683 | M59: =K56-M58-R26 -> 1.386 | N59: =K56-N58-R26 -> 0.792 | O59: =K56-O58-R26 -> 0.198 | Q59: =K56-Q58-R26 -> -0.99
I60: Shopify Basic
I61: Procentuele kosten | J61: =VLOOKUP(I60,Fees!B:J,8,FALSE) -> 0.029 | K61: =K$56*$J61 -> 0.17226 | L61: =L$56*$J61 -> 0.163647 | M61: =M$56*$J61 -> 0.155034 | N61: =N$56*$J61 -> 0.137808 | O61: =O$56*$J61 -> 0.120582 | Q61: =Q$56*$J61 -> 0.08613
I62: Vaste kosten | J62: =VLOOKUP(I60,Fees!B:J,9,FALSE) -> 0.506 | K62: =$J62 -> 0.506 | L62: =$J62 -> 0.506 | M62: =$J62 -> 0.506 | N62: =$J62 -> 0.506 | O62: =$J62 -> 0.506 | Q62: =$J62 -> 0.506
I63: Totale kosten | K63: =K61+K62 -> 0.67826 | L63: =L61+L62 -> 0.669647 | M63: =M61+M62 -> 0.661034 | N63: =N61+N62 -> 0.643808 | O63: =O61+O62 -> 0.626582 | Q63: =Q61+Q62 -> 0.59213
I64: ="Winst na kosten" &" ("&Input!$C$13&")" -> Winst na kosten (€) | K64: =K$56-K$57-K63 -> 1.30174 | L64: =L$56-L$57-L63 -> 1.013353 | M64: =M$56-M$57-M63 -> 0.724966 | N64: =N$56-N$57-N63 -> 0.148192 | O64: =O$56-O$57-O63 -> -0.428582 | Q64: =Q$56-Q$57-Q63 -> -1.58213
I65: Etsy
I66: Procentuele kosten | J66: =VLOOKUP(I65,Fees!B:J,8,FALSE) -> 0.095 | K66: =K$56*$J66 -> 0.5643 | L66: =L$56*$J66 -> 0.536085 | M66: =M$56*$J66 -> 0.50787 | N66: =N$56*$J66 -> 0.45144 | O66: =O$56*$J66 -> 0.39501 | Q66: =Q$56*$J66 -> 0.28215
I67: Vaste kosten | J67: =VLOOKUP(I65,Fees!B:J,9,FALSE) -> 0.45 | K67: =$J67 -> 0.45 | L67: =$J67 -> 0.45 | M67: =$J67 -> 0.45 | N67: =$J67 -> 0.45 | O67: =$J67 -> 0.45 | Q67: =$J67 -> 0.45
I68: Totale kosten | K68: =K66+K67 -> 1.0143 | L68: =L66+L67 -> 0.986085 | M68: =M66+M67 -> 0.95787 | N68: =N66+N67 -> 0.90144 | O68: =O66+O67 -> 0.84501 | Q68: =Q66+Q67 -> 0.73215 | U68: Staffelprijzen (dynamisch o.b.v. K35) | X68: Min. prijs | Y68: Verzending
I69: ="Winst na kosten" &" ("&Input!$C$13&")" -> Winst na kosten (€) | K69: =K$56-K$57-K68 -> 0.9657 | L69: =L$56-L$57-L68 -> 0.696915 | M69: =M$56-M$57-M68 -> 0.42813 | N69: =N$56-N$57-N68 -> -0.10944 | O69: =O$56-O$57-O68 -> -0.64701 | Q69: =Q$56-Q$57-Q68 -> -1.72215 | U69: Aannames | V69: Bol.com (incl. verz.) | W69: Etsy (incl. verz.) | X69: Doelwinst totaal | Y69: 4.15
I70: Etsy Offside Ads 15% | U70: Aantal | V70: Bol.com (incl. verz.) | W70: Etsy (incl. verz.) | X70: Shopify (excl. verz.) | Y70: Kost/stuk
I71: Procentuele kosten | J71: =VLOOKUP(I70,Fees!B:J,8,FALSE) -> 0.245 | K71: =K$56*$J71 -> 1.4553 | L71: =L$56*$J71 -> 1.382535 | M71: =M$56*$J71 -> 1.30977 | N71: =N$56*$J71 -> 1.16424 | O71: =O$56*$J71 -> 1.01871 | Q71: =Q$56*$J71 -> 0.72765 | U71: 1 | V71: =CEILING(((($K$35-$K$29-$K$30-$K$31-$K$32-$K$33)*U71*1.02 + $K$29+$K$30+$K$31+$K$32+$K$33)+$Y$69+X76+VLOOKUP("Bol.com",Fees!B:J,9,FALSE))/(1-Input!$C$16/(1+Input!$C$16)-VLOOKUP("Bol.com",Fees!B:J,8,FALSE)),0.05)-0.05 -> 16.75 | W71: =CEILING(((($K$35-$K$29-$K$30-$K$31-$K$32-$K$33)*U71*1.02 + $K$29+$K$30+$K$31+$K$32+$K$33)+$Y$69+X76+VLOOKUP("Etsy ",Fees!B:J,9,FALSE))/(1-Input!$C$16/(1+Input!$C$16)-VLOOKUP("Etsy ",Fees!B:J,8,FALSE)),0.05)-0.05 -> 14.45 | X71: =CEILING(((($K$35-$K$29-$K$30-$K$31-$K$32-$K$33)*U71*1.02 + $K$29+$K$30+$K$31+$K$32+$K$33)+X76+VLOOKUP("Shopify Basic",Fees!B:J,9,FALSE))/(1-Input!$C$16/(1+Input!$C$16)-VLOOKUP("Shopify Basic",Fees!B:J,8,FALSE)),0.05)-0.05 -> 8.15
I72: Vaste kosten | J72: =VLOOKUP(I70,Fees!B:J,9,FALSE) -> 0.45 | K72: =$J72 -> 0.45 | L72: =$J72 -> 0.45 | M72: =$J72 -> 0.45 | N72: =$J72 -> 0.45 | O72: =$J72 -> 0.45 | Q72: =$J72 -> 0.45 | U72: 5 | V72: =CEILING(((($K$35-$K$29-$K$30-$K$31-$K$32-$K$33)*U72*1.02 + $K$29+$K$30+$K$31+$K$32+$K$33)+$Y$69+X77+VLOOKUP("Bol.com",Fees!B:J,9,FALSE))/(1-Input!$C$16/(1+Input!$C$16)-VLOOKUP("Bol.com",Fees!B:J,8,FALSE)),0.05)-0.05 -> 33.05 | W72: =CEILING(((($K$35-$K$29-$K$30-$K$31-$K$32-$K$33)*U72*1.02 + $K$29+$K$30+$K$31+$K$32+$K$33)+$Y$69+X77+VLOOKUP("Etsy ",Fees!B:J,9,FALSE))/(1-Input!$C$16/(1+Input!$C$16)-VLOOKUP("Etsy ",Fees!B:J,8,FALSE)),0.05)-0.05 -> 29.55 | X72: =CEILING(((($K$35-$K$29-$K$30-$K$31-$K$32-$K$33)*U72*1.02 + $K$29+$K$30+$K$31+$K$32+$K$33)+X77+VLOOKUP("Shopify Basic",Fees!B:J,9,FALSE))/(1-Input!$C$16/(1+Input!$C$16)-VLOOKUP("Shopify Basic",Fees!B:J,8,FALSE)),0.05)-0.05 -> 21.95 | Y72: =V72/U72 -> 6.61
I73: Totale kosten | K73: =K71+K72 -> 1.9053 | L73: =L71+L72 -> 1.832535 | M73: =M71+M72 -> 1.75977 | N73: =N71+N72 -> 1.61424 | O73: =O71+O72 -> 1.46871 | Q73: =Q71+Q72 -> 1.17765 | U73: 10 | V73: =CEILING(((($K$35-$K$29-$K$30-$K$31-$K$32-$K$33)*U73*1.02 + $K$29+$K$30+$K$31+$K$32+$K$33)+$Y$69+X78+VLOOKUP("Bol.com",Fees!B:J,9,FALSE))/(1-Input!$C$16/(1+Input!$C$16)-VLOOKUP("Bol.com",Fees!B:J,8,FALSE)),0.05)-0.05 -> 52.3 | W73: =CEILING(((($K$35-$K$29-$K$30-$K$31-$K$32-$K$33)*U73*1.02 + $K$29+$K$30+$K$31+$K$32+$K$33)+$Y$69+X78+VLOOKUP("Etsy ",Fees!B:J,9,FALSE))/(1-Input!$C$16/(1+Input!$C$16)-VLOOKUP("Etsy ",Fees!B:J,8,FALSE)),0.05)-0.05 -> 47.35 | X73: =CEILING(((($K$35-$K$29-$K$30-$K$31-$K$32-$K$33)*U73*1.02 + $K$29+$K$30+$K$31+$K$32+$K$33)+X78+VLOOKUP("Shopify Basic",Fees!B:J,9,FALSE))/(1-Input!$C$16/(1+Input!$C$16)-VLOOKUP("Shopify Basic",Fees!B:J,8,FALSE)),0.05)-0.05 -> 38.3 | Y73: =V73/U73 -> 5.23
I74: ="Winst na kosten" &" ("&Input!$C$13&")" -> Winst na kosten (€) | K74: =K$56-K$57-K73 -> 0.0747 | L74: =L$56-L$57-L73 -> -0.149535 | M74: =M$56-M$57-M73 -> -0.37377 | N74: =N$56-N$57-N73 -> -0.82224 | O74: =O$56-O$57-O73 -> -1.27071 | Q74: =Q$56-Q$57-Q73 -> -2.16765
I75: Bol.com | U75: Hoe het werkt: | W75: Doelwinst per pakket:
I76: Procentuele kosten | J76: =VLOOKUP(I75,Fees!B:J,8,FALSE) -> 0.15 | K76: =(K$56+$J$80)*$J76 -> 0.891 | L76: =(L$56+$J$80)*$J76 -> 0.84645 | M76: =(M$56+$J$80)*$J76 -> 0.8019 | N76: =(N$56+$J$80)*$J76 -> 0.7128 | O76: =(O$56+$J$80)*$J76 -> 0.6237 | Q76: =(Q$56+$J$80)*$J76 -> 0.4455 | U76: • Past zich automatisch aan op K35 (productiekost per plaat) | W76: 1 stuk: | X76: 2
I77: Vaste kosten | J77: =VLOOKUP(I75,Fees!B:J,9,FALSE) -> 1.2 | K77: =$J77 -> 1.2 | L77: =$J77 -> 1.2 | M77: =$J77 -> 1.2 | N77: =$J77 -> 1.2 | O77: =$J77 -> 1.2 | Q77: =$J77 -> 1.2 | U77: • Bol/Etsy = incl. verzending; Shopify = excl. verzending | W77: 5 stuks: | X77: 5
B78: Farmloop instellingen (alleen actief als modus = Farmloop): | I78: Totale kosten | K78: =K76+K77 -> 2.091 | L78: =L76+L77 -> 2.04645 | M78: =M76+M77 -> 2.0019 | N78: =N76+N77 -> 1.9128 | O78: =O76+O77 -> 1.8237 | Q78: =Q76+Q77 -> 1.6455 | U78: • Korting per stuk: 5-pack 15%, 10-pack 25% | W78: 10 stuks: | X78: 8
B79: Stuks per plaat | C79: 10 | D79: Plaat-totaal gram | E79: 281 | F79: Plaat-totaal uren | G79: 8 | H79: Plaat-totaal min | I79: 34 | K79: =(K$56+$J$80)-K$57-K78-$J$80 -> -0.111 | L79: =(L$56+$J$80)-L$57-L78-$J$80 -> -0.36345 | M79: =(M$56+$J$80)-M$57-M78-$J$80 -> -0.6159 | N79: =(N$56+$J$80)-N$57-N78-$J$80 -> -1.1208 | O79: =(O$56+$J$80)-O$57-O78-$J$80 -> -1.6257 | Q79: =(Q$56+$J$80)-Q$57-Q78-$J$80 -> -2.6355 | U79: • Gele cellen aanpasbaar: verzendkost (W69), aantal per plaat (Y69)

Sheet Input
B8: Invoer
B9: Item | C9: Waarde | D9: Eenheid
B10: Energiekosten | C10: 0.21 | D10: =$C$13&"/kWh" -> €/kWh
B11: Arbeidskosten | C11: 20 | D11: =$C$13&"/h" -> €/h
B12: Mislukkingspercentage | C12: 2 | D12: %
B13: Valuta-eenheid | C13: € | D13: Valuta
B14: Bestellingen per maand | C14: 100 | D14: Bestellingen
B15: Abonnementen | C15: 50 | D15: =$C$13 -> €
B16: BTW-tarief | C16: 0.21 | D16: %

Sheet Printers
B8: Printers
B9: Printernaam | C9: Prijs | E9: Servicekosten over levensduur | G9: Afschrijvingsduur (Printeruren) | H9: Kosten per uur | J9: Watt voor printen per uur (W)
B10: Bambu Lab X1-Carbon Combo | C10: 1450 | D10: =Input!$C$13 -> € | E10: 400 | F10: =Input!$C$13 -> € | G10: 5000 | H10: =IFERROR((C10+E10)/G10,"-") -> 0.37 | I10: =Input!$C$13 -> € | J10: 250
B11: Bambu Lab X1-Carbon | C11: 1200 | D11: =Input!$C$13 -> € | E11: 350 | F11: =Input!$C$13 -> € | G11: 5000 | H11: =IFERROR((C11+E11)/G11,"-") -> 0.31 | I11: =Input!$C$13 -> € | J11: 250
B12: Bambu Lab P1S Combo | C12: 950 | D12: =Input!$C$13 -> € | E12: 400 | F12: =Input!$C$13 -> € | G12: 5000 | H12: =IFERROR((C12+E12)/G12,"-") -> 0.27 | I12: =Input!$C$13 -> € | J12: 250
B13: Bambu Lab P1S | C13: 700 | D13: =Input!$C$13 -> € | E13: 350 | F13: =Input!$C$13 -> € | G13: 5000 | H13: =IFERROR((C13+E13)/G13,"-") -> 0.21 | I13: =Input!$C$13 -> € | J13: 150
B14: Bambu Lab P1P | C14: 550 | D14: =Input!$C$13 -> € | E14: 350 | F14: =Input!$C$13 -> € | G14: 5000 | H14: =IFERROR((C14+E14)/G14,"-") -> 0.18 | I14: =Input!$C$13 -> € | J14: 180
B15: Bambu Lab A1 Combo | C15: 560 | D15: =Input!$C$13 -> € | E15: 250 | F15: =Input!$C$13 -> € | G15: 3000 | H15: =IFERROR((C15+E15)/G15,"-") -> 0.27 | I15: =Input!$C$13 -> € | J15: 120
B16: Bambu Lab A1 | C16: 400 | D16: =Input!$C$13 -> € | E16: 200 | F16: =Input!$C$13 -> € | G16: 3000 | H16: =IFERROR((C16+E16)/G16,"-") -> 0.2 | I16: =Input!$C$13 -> € | J16: 120
B17: Bambu Lab A1 mini Combo | C17: 460 | D17: =Input!$C$13 -> € | E17: 200 | F17: =Input!$C$13 -> € | G17: 3000 | H17: =IFERROR((C17+E17)/G17,"-") -> 0.22 | I17: =Input!$C$13 -> € | J17: 80
B18: Bambu Lab A1 mini | C18: 300 | D18: =Input!$C$13 -> € | E18: 150 | F18: =Input!$C$13 -> € | G18: 3000 | H18: =IFERROR((C18+E18)/G18,"-") -> 0.15 | I18: =Input!$C$13 -> € | J18: 80
B19: Prusa MK4S | C19: 1100 | D19: =Input!$C$13 -> € | E19: 350 | F19: =Input!$C$13 -> € | G19: 5000 | H19: =IFERROR((C19+E19)/G19,"-") -> 0.29 | I19: =Input!$C$13 -> € | J19: 120
B20: Prusa Mini+ | C20: 460 | D20: =Input!$C$13 -> € | E20: 200 | F20: =Input!$C$13 -> € | G20: 3000 | H20: =IFERROR((C20+E20)/G20,"-") -> 0.22 | I20: =Input!$C$13 -> € | J20: 80
B21: Bambu Lab P2S Combo | C21: 729 | D21: =Input!$C$13 -> € | E21: 400 | F21: =Input!$C$13 -> € | G21: 5000 | H21: =IFERROR((C21+E21)/G21,"-") -> 0.2258 | I21: =Input!$C$13 -> € | J21: 250
D22: =Input!$C$13 -> € | F22: =Input!$C$13 -> € | H22: =IFERROR((C22+E22)/G22,"-") -> - | I22: =Input!$C$13 -> €
D23: =Input!$C$13 -> € | F23: =Input!$C$13 -> € | H23: =IFERROR((C23+E23)/G23,"-") -> - | I23: =Input!$C$13 -> €
D24: =Input!$C$13 -> € | F24: =Input!$C$13 -> € | H24: =IFERROR((C24+E24)/G24,"-") -> - | I24: =Input!$C$13 -> €
D25: =Input!$C$13 -> € | F25: =Input!$C$13 -> € | H25: =IFERROR((C25+E25)/G25,"-") -> - | I25: =Input!$C$13 -> €
D26: =Input!$C$13 -> € | F26: =Input!$C$13 -> € | H26: =IFERROR((C26+E26)/G26,"-") -> - | I26: =Input!$C$13 -> €
D27: =Input!$C$13 -> € | F27: =Input!$C$13 -> € | H27: =IFERROR((C27+E27)/G27,"-") -> - | I27: =Input!$C$13 -> €

Sheet Materials
B8: Materialen
B9: Type | C9: Filament | D9: Spoelprijs | F9: Spoelgrootte (KG) | G9: Kosten per KG
B10: PLA | C10: Polymaker Polyterra PLA | D10: 16.05 | E10: =Input!$C$13 -> € | F10: 1 | G10: =IFERROR((D10/F10),"-") -> 16.05 | H10: =Input!$C$13 -> €
B11: PETG-CF | C11: Dowell PETG-CF | D11: 17.09 | E11: =Input!$C$13 -> € | F11: 1 | G11: =IFERROR((D11/F11),"-") -> 17.09 | H11: =Input!$C$13 -> €
B12: PETG | C12: Polymaker Polylite PETG | D12: 17.05 | E12: =Input!$C$13 -> € | F12: 1 | G12: =IFERROR((D12/F12),"-") -> 17.05 | H12: =Input!$C$13 -> €
B13: PLA | C13: Bambu Lab Basic PLA | D13: 20 | E13: =Input!$C$13 -> € | F13: 1 | G13: =IFERROR((D13/F13),"-") -> 20 | H13: =Input!$C$13 -> €
B14: PLA | C14: SUNLU PLA | D14: 20 | E14: =Input!$C$13 -> € | F14: 1 | G14: =IFERROR((D14/F14),"-") -> 20 | H14: =Input!$C$13 -> €
B15: PLA | C15: Prusament PLA | D15: 20 | E15: =Input!$C$13 -> € | F15: 1 | G15: =IFERROR((D15/F15),"-") -> 20 | H15: =Input!$C$13 -> €
B16: PLA | C16: eSUN PLA+ | D16: 20 | E16: =Input!$C$13 -> € | F16: 1 | G16: =IFERROR((D16/F16),"-") -> 20 | H16: =Input!$C$13 -> €
B17: PLA | C17: Polymaker Polyterra PLA | D17: 20 | E17: =Input!$C$13 -> € | F17: 1 | G17: =IFERROR((D17/F17),"-") -> 20 | H17: =Input!$C$13 -> €
B18: PLA | C18: Polymaker Polylite PLA | D18: 20 | E18: =Input!$C$13 -> € | F18: 1 | G18: =IFERROR((D18/F18),"-") -> 20 | H18: =Input!$C$13 -> €
B19: PLA | C19: Hatchbox PLA | D19: 20 | E19: =Input!$C$13 -> € | F19: 1 | G19: =IFERROR((D19/F19),"-") -> 20 | H19: =Input!$C$13 -> €
B20: PETG | C20: Prusament PETG | D20: 20 | E20: =Input!$C$13 -> € | F20: 1 | G20: =IFERROR((D20/F20),"-") -> 20 | H20: =Input!$C$13 -> €
B21: PETG | C21: eSUN PETG | D21: 20 | E21: =Input!$C$13 -> € | F21: 1 | G21: =IFERROR((D21/F21),"-") -> 20 | H21: =Input!$C$13 -> €
... B23: PETG HF | C23: Bambu Lab PETG HF | D23: 15 | E23: =Input!$C$13 -> € | F23: 1 | G23: =IFERROR((D23/F23),"-") -> 15 | H23: =Input!$C$13 -> €
E24: =Input!$C$13 -> € | G24: =IFERROR((D24/F24),"-") -> - | H24: =Input!$C$13 -> €
E25: =Input!$C$13 -> € | G25: =IFERROR((D25/F25),"-") -> - | H25: =Input!$C$13 -> €
E26: =Input!$C$13 -> € | G26: =IFERROR((D26/F26),"-") -> - | H26: =Input!$C$13 -> €
E27: =Input!$C$13 -> € | G27: =IFERROR((D27/F27),"-") -> - | H27: =Input!$C$13 -> €
E28: =Input!$C$13 -> € | G28: =IFERROR((D28/F28),"-") -> - | H28: =Input!$C$13 -> €
E29: =Input!$C$13 -> € | G29: =IFERROR((D29/F29),"-") -> - | H29: =Input!$C$13 -> €
E30: =Input!$C$13 -> € | G30: =IFERROR((D30/F30),"-") -> - | H30: =Input!$C$13 -> €
E31: =Input!$C$13 -> € | G31: =IFERROR((D31/F31),"-") -> - | H31: =Input!$C$13 -> €
E32: =Input!$C$13 -> € | G32: =IFERROR((D32/F32),"-") -> - | H32: =Input!$C$13 -> €
E33: =Input!$C$13 -> € | G33: =IFERROR((D33/F33),"-") -> - | H33: =Input!$C$13 -> €
E34: =Input!$C$13 -> € | G34: =IFERROR((D34/F34),"-") -> - | H34: =Input!$C$13 -> €
E35: =Input!$C$13 -> € | G35: =IFERROR((D35/F35),"-") -> - | H35: =Input!$C$13 -> €
... E40: =Input!$C$13 -> € | G40: =IFERROR((D40/F40),"-") -> - | H40: =Input!$C$13 -> €

Sheet Fees
B8: Kosten
B9: Platform | C9: Maandelijks | D9: Transactie | E9: Betaling | F9: Betaling vast | G9: Plaatsingskosten | H9: Offside-advertentie | I9: Totale procentuele kosten | J9: Totale vaste kosten
B10: Shopify Basic | C10: 20.6 | E10: 0.029 | F10: 0.3 | I10: =IF(D10+E10+H10=0,"",D10+E10+H10) -> 0.029 | J10: =IF(C10/Input!$C$14+F10+G10=0,"",C10/Input!$C$14+F10+G10) -> 0.506
B11: Shopify Shopify | C11: 79 | E11: 0.026 | F11: 0.3 | I11: =IF(D11+E11+H11=0,"",D11+E11+H11) -> 0.026 | J11: =IF(C11/Input!$C$14+F11+G11=0,"",C11/Input!$C$14+F11+G11) -> 1.09
B12: Etsy | D12: 0.065 | E12: 0.03 | F12: 0.25 | G12: 0.2 | I12: =IF(D12+E12+H12=0,"",D12+E12+H12) -> 0.095 | J12: =IF(C12/Input!$C$14+F12+G12=0,"",C12/Input!$C$14+F12+G12) -> 0.45
B13: Etsy Offside Ads 15% | D13: 0.065 | E13: 0.03 | F13: 0.25 | G13: 0.2 | H13: 0.15 | I13: =IF(D13+E13+H13=0,"",D13+E13+H13) -> 0.245 | J13: =IF(C13/Input!$C$14+F13+G13=0,"",C13/Input!$C$14+F13+G13) -> 0.45
B14: Etsy Offside Ads 12% | D14: 0.065 | E14: 0.03 | F14: 0.25 | G14: 0.2 | H14: 0.12 | I14: =IF(D14+E14+H14=0,"",D14+E14+H14) -> 0.215 | J14: =IF(C14/Input!$C$14+F14+G14=0,"",C14/Input!$C$14+F14+G14) -> 0.45
B15: eBay Starter | C15: 4.95 | D15: 0.129 | E15: 0.029 | F15: 0.3 | I15: =IF(D15+E15+H15=0,"",D15+E15+H15) -> 0.158 | J15: =IF(C15/Input!$C$14+F15+G15=0,"",C15/Input!$C$14+F15+G15) -> 0.3495
B16: eBay Basic | C16: 21.95 | D16: 0.12 | E16: 0.029 | F16: 0.3 | I16: =IF(D16+E16+H16=0,"",D16+E16+H16) -> 0.149 | J16: =IF(C16/Input!$C$14+F16+G16=0,"",C16/Input!$C$14+F16+G16) -> 0.5195
B17: eBay Premium | C17: 59.95 | D17: 0.115 | E17: 0.029 | F17: 0.3 | I17: =IF(D17+E17+H17=0,"",D17+E17+H17) -> 0.144 | J17: =IF(C17/Input!$C$14+F17+G17=0,"",C17/Input!$C$14+F17+G17) -> 0.8995
B18: Amazon FBM Individual | D18: 0.15 | G18: 0.99 | I18: =IF(D18+E18+H18=0,"",D18+E18+H18) -> 0.15 | J18: =IF(C18/Input!$C$14+F18+G18=0,"",C18/Input!$C$14+F18+G18) -> 0.99
B19: Amazon FBM Pro | C19: 39.99 | D19: 0.15 | I19: =IF(D19+E19+H19=0,"",D19+E19+H19) -> 0.15 | J19: =IF(C19/Input!$C$14+F19+G19=0,"",C19/Input!$C$14+F19+G19) -> 0.3999
B20: Bol.com | C20: 0 | D20: 0.15 | E20: 0 | F20: 1.2 | G20: 0 | H20: 0 | I20: =IF(D20+E20+H20=0,"",D20+E20+H20) -> 0.15 | J20: =IF(C20/Input!$C$14+F20+G20=0,"",C20/Input!$C$14+F20+G20) -> 1.2
I21: =IF(D21+E21+H21=0,"",D21+E21+H21) | J21: =IF(C21/Input!$C$14+F21+G21=0,"",C21/Input!$C$14+F21+G21)
I22: =IF(D22+E22+H22=0,"",D22+E22+H22) | J22: =IF(C22/Input!$C$14+F22+G22=0,"",C22/Input!$C$14+F22+G22)
I23: =IF(D23+E23+H23=0,"",D23+E23+H23) | J23: =IF(C23/Input!$C$14+F23+G23=0,"",C23/Input!$C$14+F23+G23)
I24: =IF(D24+E24+H24=0,"",D24+E24+H24) | J24: =IF(C24/Input!$C$14+F24+G24=0,"",C24/Input!$C$14+F24+G24)
I25: =IF(D25+E25+H25=0,"",D25+E25+H25) | J25: =IF(C25/Input!$C$14+F25+G25=0,"",C25/Input!$C$14+F25+G25)
I26: =IF(D26+E26+H26=0,"",D26+E26+H26) | J26: =IF(C26/Input!$C$14+F26+G26=0,"",C26/Input!$C$14+F26+G26)
I27: =IF(D27+E27+H27=0,"",D27+E27+H27) | J27: =IF(C27/Input!$C$14+F27+G27=0,"",C27/Input!$C$14+F27+G27)
